{"textures":{"0":"modelengine:entity/smaug","particle":"#0"},"elements":[{"from":[-14.8667755,8.0,-14.751968],"to":[9.041733,8.0,9.248032],"faces":{"up":{"uv":[4.40625,0.75,4.78125,0.375],"tintindex":0,"rotation":0,"texture":"#0"},"down":{"uv":[4.40625,0.75,4.78125,1.125],"tintindex":0,"rotation":0,"texture":"#0"}}},{"from":[7.070755,8.0,-14.7599945],"to":[30.979248,8.0,9.2400055],"faces":{"up":{"uv":[4.40625,1.5,4.78125,1.125],"tintindex":0,"rotation":0,"texture":"#0"},"down":{"uv":[0.0,4.46875,0.375,4.84375],"tintindex":0,"rotation":0,"texture":"#0"}}},{"from":[7.070755,8.0,6.4524994],"to":[30.979248,8.0,28.272507],"faces":{"up":{"uv":[9.375,4.84375,9.75,4.5],"tintindex":0,"rotation":0,"texture":"#0"},"down":{"uv":[4.84375,9.375,5.21875,9.71875],"tintindex":0,"rotation":0,"texture":"#0"}}}],"display":{"head":{"rotation":[0.0,0.0,0.0]},"firstperson_righthand":{"rotation":[0.0,0.0,0.0]},"thirdperson_lefthand":{"rotation":[0.0,-0.0,-0.0]},"firstperson_lefthand":{"rotation":[0.0,-0.0,-0.0]},"fixed":{"rotation":[0.0,0.0,0.0]},"ground":{"rotation":[0.0,0.0,0.0]},"thirdperson_righthand":{"rotation":[0.0,0.0,0.0]},"gui":{"rotation":[-150.0,-45.0,180.0]}}}